MANIFEST.in
README.rst
setup.py
django_leetchi.egg-info/PKG-INFO
django_leetchi.egg-info/SOURCES.txt
django_leetchi.egg-info/dependency_links.txt
django_leetchi.egg-info/not-zip-safe
django_leetchi.egg-info/pbr.json
django_leetchi.egg-info/requires.txt
django_leetchi.egg-info/top_level.txt
djleetchi/__init__.py
djleetchi/api.py
djleetchi/compat.py
djleetchi/constants.py
djleetchi/encoders.py
djleetchi/fields.py
djleetchi/forms.py
djleetchi/helpers.py
djleetchi/http.py
djleetchi/models.py
djleetchi/operations.py
djleetchi/settings.py
djleetchi/tasks.py
djleetchi/urls.py
djleetchi/util.py
djleetchi/views.py
djleetchi/locale/de/LC_MESSAGES/django.mo
djleetchi/locale/de/LC_MESSAGES/django.po
djleetchi/locale/en/LC_MESSAGES/django.mo
djleetchi/locale/en/LC_MESSAGES/django.po
djleetchi/locale/es/LC_MESSAGES/django.mo
djleetchi/locale/es/LC_MESSAGES/django.po
djleetchi/locale/fr/LC_MESSAGES/django.mo
djleetchi/locale/fr/LC_MESSAGES/django.po
djleetchi/locale/it/LC_MESSAGES/django.mo
djleetchi/locale/it/LC_MESSAGES/django.po
djleetchi/locale/pt/LC_MESSAGES/django.mo
djleetchi/locale/pt/LC_MESSAGES/django.po
djleetchi/management/__init__.py
djleetchi/management/commands/__init__.py
djleetchi/management/commands/sync_resources.py
djleetchi/management/commands/sync_wallet_amount.py
djleetchi/migrations/0001_initial.py
djleetchi/migrations/0002_auto__chg_field_contribution_contribution__chg_field_refund_refund__ch.py
djleetchi/migrations/0003_auto__add_field_contribution_card_expiration_date__add_field_contribut.py
djleetchi/migrations/0004_auto__add_field_contribution_payment_url.py
djleetchi/migrations/0005_auto__add_field_contribution_culture.py
djleetchi/migrations/0006_auto__del_field_contribution_payment_url__add_field_contribution_payme.py
djleetchi/migrations/__init__.py
djleetchi/templatetags/__init__.py
djleetchi/templatetags/leetchi_tags.py
djleetchi/tests/__init__.py
djleetchi/tests/settings.py
djleetchi/tests/tests.py