Metadata-Version: 1.1
Name: django-leetchi
Version: 0.1.20
Summary: An integration of python-leetchi with Django framework
Home-page: http://github.com/thoas/django-leetchi
Author: Florent Messa
Author-email: florent.messa@gmail.com
License: UNKNOWN
Platform: UNKNOWN
Classifier: Environment :: Web Environment
Classifier: Intended Audience :: Developers
Classifier: License :: OSI Approved :: MIT License
Classifier: Operating System :: OS Independent
Classifier: Programming Language :: Python
Classifier: Topic :: Utilities
